gazix/__init__.py
gazix/cli.py
gazix/api/gitlab_api_MR.py
gazix/api/gitlab_api_access.py
gazix/api/gitlab_api_label.py
gazix/api/gitlab_api_object.py
gazix/api/gitlab_api_pipeline.py
gazix/api/gitlab_api_queries.py
gazix/arguments/arguments.py
gazix/automerge/disable.py
gazix/draft/draft.py
gazix/kill/kill.py
gazix/kill/kill_old.py
gazix/migration/labels.py
gazix/migration/migration.py
gazix/migration/mr.py
gazix/trigger/trigger.py
gazix/utils/__init__.py
gazix/utils/command.py
gazix/utils/file.py
gazix/utils/json.py
gazix/utils/log.py
gazix/utils/option.py
gazix-1.5.2.dist-info/METADATA
gazix-1.5.2.dist-info/WHEEL
gazix-1.5.2.dist-info/entry_points.txt
gazix-1.5.2.dist-info/licenses/LICENSE
gazix-1.5.2.dist-info/RECORD
