Metadata-Version: 2.1
Name: gazix
Version: 1.5.2
Summary: Programs to manipulate the GitLab-CI API for the project alya
Project-URL: Homepage, https://alya.gitlab.bsc.es/alya/ci-cd/gazix
Project-URL: Bug Tracker, https://alya.gitlab.bsc.es/alya/ci-cd/gazix/issues
Author-email: Damien Dosimont <damien.dosimont@gmail.com>
License-File: LICENSE
Classifier: License :: OSI Approved :: GNU General Public License v3 or later (GPLv3+)
Classifier: Operating System :: POSIX :: Linux
Classifier: Programming Language :: Python :: 3
Requires-Python: >=3.7
